gitcd/__init__.py
gitcd/exceptions.py
gitcd/package.py
gitcd/app/__init__.py
gitcd/app/clean.py
gitcd/app/release.py
gitcd/app/upgrade.py
gitcd/bin/__init__.py
gitcd/bin/console.py
gitcd/bin/kivy.py
gitcd/config/__init__.py
gitcd/config/defaults.py
gitcd/git/__init__.py
gitcd/git/branch.py
gitcd/git/exceptions.py
gitcd/git/nullRepository.py
gitcd/git/remote.py
gitcd/git/repository.py
gitcd/git/tag.py
gitcd/git/server/__init__.py
gitcd/git/server/bitbucket.py
gitcd/git/server/github.py
gitcd/git/server/gitlab.py
gitcd/interface/__init__.py
gitcd/interface/cli/__init__.py
gitcd/interface/cli/abstract.py
gitcd/interface/cli/clean.py
gitcd/interface/cli/compare.py
gitcd/interface/cli/finish.py
gitcd/interface/cli/init.py
gitcd/interface/cli/refresh.py
gitcd/interface/cli/release.py
gitcd/interface/cli/review.py
gitcd/interface/cli/start.py
gitcd/interface/cli/status.py
gitcd/interface/cli/test.py
gitcd/interface/cli/upgrade.py
gitcd/interface/cli/version.py
gitcd/interface/kivy/__init__.py
gitcd/interface/kivy/branchpanel.py
gitcd/interface/kivy/clean.py
gitcd/interface/kivy/infopanel.py
gitcd/interface/kivy/mainpanel.py
gitcd/interface/kivy/navigation.py
gitcd/interface/kivy/panel.py
gitcd/interface/kivy/tagpanel.py
gitcd/interface/kivy/upgrade.py
gitcd-2.2.3.dist-info/LICENSE
gitcd-2.2.3.dist-info/METADATA
gitcd-2.2.3.dist-info/WHEEL
gitcd-2.2.3.dist-info/entry_points.txt
gitcd-2.2.3.dist-info/top_level.txt
gitcd-2.2.3.dist-info/RECORD
