Metadata-Version: 2.1
Name: gitcd
Version: 2.2.3
Summary: Tool for continuous delivery using git
Home-page: https://www.gitcd.io
Author: Claudio Walser
Author-email: info@gitcd.io
License: Apache License
Keywords: git,application,continuos delivery
Platform: UNKNOWN
Classifier: Development Status :: 5 - Production/Stable
Classifier: Environment :: Console
Classifier: Intended Audience :: Developers
Classifier: License :: OSI Approved :: Apache Software License
Classifier: Operating System :: OS Independent
Classifier: Programming Language :: Python :: 3.5
Classifier: Programming Language :: Python :: 3.6
Classifier: Programming Language :: Python :: 3.7
Classifier: Programming Language :: Python :: 3.8
Classifier: Topic :: Utilities
Requires-Dist: simpcli
Requires-Dist: pyyaml
Requires-Dist: argparse
Requires-Dist: argcomplete
Requires-Dist: requests
Requires-Dist: packaging
Requires-Dist: typing
